pybdedata/__init__.py
pybdedata/query.py
pybdedata-0.0.5.dist-info/LICENSE
pybdedata-0.0.5.dist-info/METADATA
pybdedata-0.0.5.dist-info/WHEEL
pybdedata-0.0.5.dist-info/top_level.txt
pybdedata-0.0.5.dist-info/RECORD
