Metadata-Version: 2.1
Name: pybdedata
Version: 0.0.5
Summary: A module to access data from the Mauro Borges Statistic and Socioeconomic Institute (IMB), Goias - Brazil
Home-page: https://github.com/boliveirageo/pybdedata
Author: Bernard Silva de Oliveira
Author-email: bernard.oliveira@goias.gov.br
License: MIT License
Keywords: statistics,data,IMB,Mauro Borges,Brazil
License-File: LICENSE
Requires-Dist: requests
